nixl_cu12/py.typed
nixl_cu12/_api.py
nixl_cu12/_utils.cpython-311-aarch64-linux-gnu.so
nixl_cu12/__init__.py
nixl_cu12/logging.py
nixl_cu12/_bindings.cpython-311-aarch64-linux-gnu.so
nixl_cu12.scripts/nixl_example
nixl_cu12.scripts/telemetry_reader
nixl_cu12.scripts/nixl_etcd_example
nixl_cu12.libs/libabsl_log_internal_log_sink_set-940303ed.so.2501.0.0
nixl_cu12.libs/libabsl_throw_delegate-0c5f193a.so.2501.0.0
nixl_cu12.libs/libabsl_vlog_config_internal-e1eac39b.so.2501.0.0
nixl_cu12.libs/libabsl_flags_private_handle_accessor-d1ae142c.so.2501.0.0
nixl_cu12.libs/libre2-c22bb8f5.so.9.0.0
nixl_cu12.libs/libaio-eecdd17c.so.1.0.1
nixl_cu12.libs/libabsl_random_internal_seed_material-108c07f5.so.2501.0.0
nixl_cu12.libs/libabsl_strings-207fe037.so.2501.0.0
nixl_cu12.libs/libaws-c-common-0aef05d0.so.1.0.0
nixl_cu12.libs/libmlx5-15de22f6.so.1.24.48.0
nixl_cu12.libs/libabsl_kernel_timeout_internal-920ec207.so.2501.0.0
nixl_cu12.libs/libprotobuf-05333177.so.31.0.0
nixl_cu12.libs/libabsl_raw_hash_set-4bf61660.so.2501.0.0
nixl_cu12.libs/libabsl_random_internal_pool_urbg-b67fe273.so.2501.0.0
nixl_cu12.libs/libdoca_gpunetio-ac379177.so.3.2.0118
nixl_cu12.libs/libabsl_civil_time-fff56f85.so.2501.0.0
nixl_cu12.libs/libabsl_random_distributions-7a5be66b.so.2501.0.0
nixl_cu12.libs/libabsl_city-8e3b82f1.so.2501.0.0
nixl_cu12.libs/libabsl_log_internal_format-322e1a85.so.2501.0.0
nixl_cu12.libs/libpull-13d20d79.so.1.3.0
nixl_cu12.libs/libabsl_die_if_null-86be5989.so.2501.0.0
nixl_cu12.libs/libabsl_random_internal_randen_hwaes-6f2e3fef.so.2501.0.0
nixl_cu12.libs/libupb_base_lib-f6e1974b.so.48.0.0
nixl_cu12.libs/libabsl_time-f16bbb35.so.2501.0.0
nixl_cu12.libs/libabsl_random_internal_platform-d6dba588.so.2501.0.0
nixl_cu12.libs/libabsl_bad_optional_access-8be63053.so.2501.0.0
nixl_cu12.libs/libupb_wire_lib-bdae4e8a.so.48.0.0
nixl_cu12.libs/libaws-crt-cpp-4541d8c2.so
nixl_cu12.libs/libabsl_log_internal_nullguard-aa24dacc.so.2501.0.0
nixl_cu12-0.9.0.dist-info/METADATA
nixl_cu12-0.9.0.dist-info/WHEEL
nixl_cu12-0.9.0.dist-info/RECORD
nixl_cu12-0.9.0.dist-info/sboms/auditwheel.cdx.json
nixl_cu12-0.9.0.dist-info/licenses/LICENSE
